defs.v
'define ALU_NONE                        4'b0000
'define ALU_ADD                         4'b0001
'define ALU_SUB                         4'b0010
'define ALU_AND                         4'b0011
'define ALU_OR                          4'b0100
'define ALU_XOR                         4'b0101
'define ALU_SHIFTL                      4'b0110
'define ALU_SHIFT                       4'b0111
'define ALU_SHIFTR_ARITH                4'b1000

rtl/shifter.v
module barrel_shifter(
                        input [31:0] in, 
                        input [4:0] n,
                        input dir,
                        input arith,
                        output wire [31:0] out);

reg [31:0] shift_left_1;
reg [31:0] shift_left_2;
reg [31:0] shift_left_4;
reg [31:0] shift_left_8;
reg [31:0] shift_left_16;

reg [31:0] shift_right_1;
reg [31:0] shift_right_2;
reg [31:0] shift_right_4;
reg [31:0] shift_right_8;
reg [31:0] shift_right_16;
reg [31:0] shift_right_fill; 

reg [31:0] result; 

always @(in or n or dir or arith) begin 

    result = 32'b0;
    
    shift_left_1 = 32'b0;
    shift_left_2 = 32'b0;
    shift_left_4 = 32'b0;
    shift_left_8 = 32'b0;
    shift_left_16 = 32'b0;

    shift_right_1 = 32'b0;
    shift_right_2 = 32'b0;
    shift_right_4 = 32'b0;
    shift_right_8 = 32'b0;
    shift_right_16 = 32'b0; 
    shift_right_fill = 32'b0;

    
    
    if(dir==0) begin //left shift

        if(n[0] == 1'b1)
            shift_left_1 = {in[30:0],1'b0};
        else
            shift_left_1 = in; 
            
        if(n[1] == 1'b1)
            shift_left_2 = {shift_left_1[29:0], 2'b00};
        else 
            shift_left_2 = shift_left_1; 
        
        if (n[2] == 1'b1)
            shift_left_4 = {shift_left_2[27:0], 4'b0000};
        else 
            shift_left_4 = shift_left_2;
        
        if (n[3] == 1'b1)
            shift_left_8 = {shift_left_4[23:0], 8'b00000000};
        else
            shift_left_8 = shift_left_4;
        
        if(n[4] == 1'b1)
            shift_left_16 = {shift_left_8[15:0], 16'b0000000000000000};
        else
            shift_left_16 = shift_left_8;
        
        result = shift_left_16; 

      
    end else begin  //right shift


        if (in[31] == 1 && arith == 1) 
            shift_right_fill = 32'hFFFFFFFF;
        else
            shift_right_fill = 32'h00000000;

        if(n[0] == 1'b1)
            shift_right_1 = {shift_right_fill[31], in[31:1]};
        else 
            shift_right_1 = in;

        if(n[1] == 1'b1)
            shift_right_2 = {shift_right_fill[31:30], shift_right_1[31:2]};
        else
            shift_right_2 = shift_right_1;
        
        if(n[2] == 1'b1)
            shift_right_4 = {shift_right_fill[31:28], shift_right_2[31:4]};
        else
            shift_right_4 = shift_right_2;
            
        if(n[3] == 1'b1)
            shift_right_8 = {shift_right_fill[31:24], shift_right_4[31:8]};
        else 
            shift_right_8 = shift_right_4;

        if(n[4] == 1'b1)
            shift_right_16 = {shift_right_fill[15:0], shift_right_8[31:16]};
        else 
            shift_right_16 = shift_right_8; 

        result = shift_right_16; 
        end

    end

    assign out = result; 

endmodule

rtl/alu.v
//inputs a, b operands, alu opcode, output

`include "defs.v"

module riscv_alu(  
                    input [3:0] opcode, 
                    input [31:0] a,
                    input [31:0] b,
                    output reg [31:0] out);


//control signals for shifter
wire shift_dir = (opcode == `ALU_SHIFTR || opcode == `ALU_SHIFTR_ARITH);
wire shift_arith = (opcode == `ALU_SHIFTR_ARITH); 

wire [31:0] shift_output;

barrel_shifter shifter_inst( .in(a),
                            .n(b[4:0]),
                            .dir(shift_dir),
                            .arith(shift_arith),
                            .out(shift_output)
                            );




always @(*) begin 

    out = 32'b0; 
  
    case (opcode)

    `ALU_ADD: out = (a + b);

    `ALU_SUB: out = (a-b);

    `ALU_AND: out = (a&b);
    
    `ALU_OR: out = (a|b);

    `ALU_XOR: out =  (a^b);

    `ALU_SHIFTL: out = shift_output; 

    `ALU_SHIFTR: out = shift_output; 

    `ALU_SHIFTR_ARITH: out = shift_output;

    default: out = 32'b0; 
    endcase 
end
endmodule

tb/alu_tb.v
`include "defs.v"

module alu_tb();

//alu inputs
reg [3:0] opcode; 
reg [31:0] a; 
reg [31:0] b;

//alu output
wire [31:0] out; 

riscv_alu DUT(  .opcode (opcode),
                .a (a),
                .b (b),
                .out (out));


task test_alu;
    input [3:0] op; 
    input [31:0] rs_a; 
    input [31:0] rs_b;
    input [31:0] expected; 

    begin

    opcode = op; 
    a = rs_a; 
    b = rs_b; 
    #5;

    if (out != expected)
        $display("FAIL: opcode=%b a=%h b=%h --> out=%h (expected = %h)\n\n", op, rs_a, rs_b, out, expected);

    else
        $display("PASS: opcode=%b a=%h b=%h --> out=%h\n\n", op, rs_a, rs_b, out);
    end
endtask 

//simulation

initial begin
    
    $dumpfile("waveforms/alu.vcd");
    $dumpvars(0, alu_tb);

    opcode = 4'b0;
    a = 32'b0;
    b = 32'b0;
    
    $display("ALU TEST BEGIN...\n");

    //arithmetic operations

    test_alu(`ALU_ADD, 32'd10, 32'd15, 32'd25);
    
    test_alu(`ALU_SUB, 32'd35, 32'd15, 32'd20);

    //bitwise operations

    test_alu(`ALU_AND, 32'h0FFF000F, 32'hF0FF0F0F, 32'h00FF000F);
    test_alu(`ALU_OR, 32'h0000FFFF, 32'hFFFF0000, 32'hFFFFFFFF);
    test_alu(`ALU_XOR, 32'hAAAAAAAA, 32'h55555555, 32'hFFFFFFFF);

    //shift left

    test_alu(`ALU_SHIFTL, 32'h00000001, 32'd4, 32'h00000010);
    
    //shift right (logical)

    test_alu(`ALU_SHIFTR, 32'h10000000, 32'd4, 32'h01000000);

    //shift right (arithmetic)

    test_alu(`ALU_SHIFTR_ARITH, 32'h80000000, 32'd4, 32'hF8000000);

    $display("ALU TEST END...");
    $finish;

end
endmodule

waveforms/alu.vcd
$date
	Wed Jul 30 09:01:57 2025
$end
$version
	Icarus Verilog
$end
$timescale
	1s
$end
$scope module alu_tb $end
$var wire 32 ! out [31:0] $end
$var reg 32 " a [31:0] $end
$var reg 32 # b [31:0] $end
$var reg 4 $ opcode [3:0] $end
$scope module DUT $end
$var wire 32 % a [31:0] $end
$var wire 32 & b [31:0] $end
$var wire 4 ' opcode [3:0] $end
$var wire 1 ( shift_dir $end
$var wire 32 ) shift_output [31:0] $end
$var wire 1 * shift_arith $end
$var reg 32 + out [31:0] $end
$scope module shifter_inst $end
$var wire 1 * arith $end
$var wire 1 ( dir $end
$var wire 32 , in [31:0] $end
$var wire 5 - n [4:0] $end
$var wire 32 . out [31:0] $end
$var reg 32 / result [31:0] $end
$var reg 32 0 shift_left_1 [31:0] $end
$var reg 32 1 shift_left_16 [31:0] $end
$var reg 32 2 shift_left_2 [31:0] $end
$var reg 32 3 shift_left_4 [31:0] $end
$var reg 32 4 shift_left_8 [31:0] $end
$var reg 32 5 shift_right_1 [31:0] $end
$var reg 32 6 shift_right_16 [31:0] $end
$var reg 32 7 shift_right_2 [31:0] $end
$var reg 32 8 shift_right_4 [31:0] $end
$var reg 32 9 shift_right_8 [31:0] $end
$var reg 32 : shift_right_fill [31:0] $end
$upscope $end
$upscope $end
$scope task test_alu $end
$var reg 32 ; expected [31:0] $end
$var reg 4 < op [3:0] $end
$var reg 32 = rs_a [31:0] $end
$var reg 32 > rs_b [31:0] $end
$upscope $end
$upscope $end
$enddefinitions $end
#0
$dumpvars
b1111 >
b1010 =
b1 <
b11001 ;
b0 :
b0 9
b0 8
b0 7
b0 6
b0 5
b1010000000000000000 4
b10100000000 3
b1010000 2
b1010000000000000000 1
b10100 0
b1010000000000000000 /
b1010000000000000000 .
b1111 -
b1010 ,
b11001 +
0*
b1010000000000000000 )
0(
b1 '
b1111 &
b1010 %
b1 $
b1111 #
b1010 "
b11001 !
$end
#5
b100011000000000000000 1
b100011000000000000000 4
b1000110000000 3
b100011000 2
b1000110 0
b100011000000000000000 )
b100011000000000000000 .
b100011000000000000000 /
b10100 !
b10100 +
b100011 "
b100011 %
b100011 ,
b10 $
b10 '
b10100 ;
b100011 =
b10 <
#10
b10000000000001111000000000000000 1
b10000000000001111000000000000000 4
b11111111100000000000011110000000 3
b1111111111110000000000001111000 2
b11111111111100000000000011110 0
b10000000000001111000000000000000 )
b10000000000001111000000000000000 .
b10000000000001111000000000000000 /
b111111110000000000001111 !
b111111110000000000001111 +
b11110000111111110000111100001111 #
b11110000111111110000111100001111 &
b1111111111110000000000001111 "
b1111111111110000000000001111 %
b1111111111110000000000001111 ,
b11 $
b11 '
b111111110000000000001111 ;
b11110000111111110000111100001111 >
b1111111111110000000000001111 =
b11 <
#15
b0 -
b1111111111111111 1
b1111111111111111 4
b1111111111111111 3
b1111111111111111 2
b1111111111111111 0
b1111111111111111 )
b1111111111111111 .
b1111111111111111 /
b11111111111111111111111111111111 !
b11111111111111111111111111111111 +
b11111111111111110000000000000000 #
b11111111111111110000000000000000 &
b1111111111111111 "
b1111111111111111 %
b1111111111111111 ,
b100 $
b100 '
b11111111111111111111111111111111 ;
b11111111111111110000000000000000 >
b1111111111111111 =
b100 <
#20
b10101 -
b1010101010000000000000000000000 1
b1010101010101010101010101000000 4
b1010101010101010101010101000000 3
b1010101010101010101010101010100 2
b1010101010101010101010101010100 0
b1010101010000000000000000000000 )
b1010101010000000000000000000000 .
b1010101010000000000000000000000 /
b11111111111111111111111111111111 !
b11111111111111111111111111111111 +
b1010101010101010101010101010101 #
b1010101010101010101010101010101 &
b10101010101010101010101010101010 "
b10101010101010101010101010101010 %
b10101010101010101010101010101010 ,
b101 $
b101 '
b1010101010101010101010101010101 >
b10101010101010101010101010101010 =
b101 <
#25
b100 -
b10000 1
b10000 4
b10000 3
b1 2
b1 0
b10000 )
b10000 .
b10000 /
b10000 !
b10000 +
b100 #
b100 &
b1 "
b1 %
b1 ,
b110 $
b110 '
b10000 ;
b100 >
b1 =
b110 <
#30
b1000000000000000000000000 6
b1000000000000000000000000 9
b1000000000000000000000000 8
b10000000000000000000000000000 7
b10000000000000000000000000000 5
b0 1
b0 4
b0 3
b0 2
b0 0
b1000000000000000000000000 )
b1000000000000000000000000 .
b1000000000000000000000000 /
b1000000000000000000000000 !
b1000000000000000000000000 +
1(
b10000000000000000000000000000 "
b10000000000000000000000000000 %
b10000000000000000000000000000 ,
b111 $
b111 '
b1000000000000000000000000 ;
b10000000000000000000000000000 =
b111 <
#35
b11111000000000000000000000000000 !
b11111000000000000000000000000000 +
b11111111111111111111111111111111 :
b11111000000000000000000000000000 6
b11111000000000000000000000000000 9
b11111000000000000000000000000000 8
b10000000000000000000000000000000 7
b10000000000000000000000000000000 5
b11111000000000000000000000000000 )
b11111000000000000000000000000000 .
b11111000000000000000000000000000 /
b10000000000000000000000000000000 "
b10000000000000000000000000000000 %
b10000000000000000000000000000000 ,
1*
b1000 $
b1000 '
b11111000000000000000000000000000 ;
b10000000000000000000000000000000 =
b1000 <
